{
	"variables": [],
	"info": {
		"name": "Neighbours Kitchen",
		"_postman_id": "6bc67cd6-3227-2b89-3b7e-1b4ba96aeb44",
		"description": "",
		"schema": "https://schema.getpostman.com/json/collection/v2.0.0/collection.json"
	},
	"item": [
		{
			"name": "Registration",
			"request": {
				"url": "localhost:8080/registration",
				"method": "POST",
				"header": [
					{
						"key": "Content-Type",
						"value": "application/json",
						"description": ""
					}
				],
				"body": {
					"mode": "raw",
					"raw": "{\"username\":\"Divinesteel\",\n\t\"password\":\"jaka2957apujq!#\",\n\t\"firstName\":\"Stylianos\",\n\t\"lastName\":\"Andreolas\",\n\t\"address\":\"Kapodistrioy 7\",\n\t\"isCook\":true,\n\t\"phone\":\"6955542869\",\n\t\"enabled\":true\n}\n"
				},
				"description": ""
			},
			"response": []
		}
	]
}